{"name": "Språkpolitik", "id": 214663, "predecessors": [{"name": "Kommunikation", "id": 73797}, {"name": "Kultur", "id": 54878}], "successors": [{"name": "Språkvård", "id": 103049}, {"name": "Svenska", "id": 53225}, {"name": "Engelska", "id": 69108}, {"name": "Franska", "id": 75638}, {"name": "Finska", "id": 77982}, {"name": "Tyska", "id": 147670}, {"name": "Spanskspråkiga_författare", "id": 69539}, {"name": "Spanskspråkig_litteratur", "id": 254979}, {"name": "Spanskspråkiga_filmer", "id": 1603109}, {"name": "Spanskspråkiga_TV-serier", "id": 2083192}, {"name": "Spanskspråkig_musik", "id": 7584625}, {"name": "Spanskspråkiga_länder_och_territorier", "id": 8742123}, {"name": "Danskspråkiga_författare", "id": 85649}, {"name": "Danskspråkiga_TV-serier", "id": 1603148}, {"name": "Danskspråkiga_filmer", "id": 1615680}, {"name": "Italienskspråkiga_författare", "id": 97173}, {"name": "Italienskspråkig_litteratur", "id": 186332}, {"name": "Italienska_ord_och_uttryck", "id": 1149861}, {"name": "Italienskspråkiga_filmer", "id": 1720264}, {"name": "Italienskspråkiga_operor", "id": 7180269}, {"name": "Polskspråkiga_filmer", "id": 1720686}, {"name": "Rumänskspråkiga_författare", "id": 55709}, {"name": "Tjeckiskspråkiga_författare", "id": 245559}, {"name": "Tjeckiskspråkiga_operor", "id": 8021553}, {"name": "Portugisiskspråkiga_författare", "id": 252997}, {"name": "Portugisiskspråkiga_filmer", "id": 1720685}, {"name": "Polskspråkiga_författare", "id": 67927}, {"name": "Ungerskspråkiga_författare", "id": 97115}]}