{"name": "Fiat", "id": 332577, "predecessors": [{"name": "Multinationella_företag", "id": 608928}, {"name": "Italienska_företag", "id": 61945}, {"name": "Bilar", "id": 55125}, {"name": "Amerikanska_fordonstillverkare", "id": 1009919}, {"name": "Flyg", "id": 60557}, {"name": "Sport", "id": 55124}], "successors": [{"name": "Bilar_tillverkade_av_Fiat", "id": 249063}, {"name": "Bilar_tillverkade_av_Alfa_Romeo", "id": 331950}, {"name": "Bilar_tillverkade_av_Ferrari", "id": 398537}, {"name": "Scuderia_Ferrari", "id": 8082757}, {"name": "Bilar_tillverkade_av_Lancia", "id": 399334}, {"name": "Bilar_tillverkade_av_Maserati", "id": 432561}]}