{"name": "Svenska_rockgrupper", "id": 492733, "predecessors": [{"name": "Musik_i_Sverige", "id": 1105454}, {"name": "Musikgenrer", "id": 56587}, {"name": "Topp", "id": 113605}], "successors": [{"name": "Svenska_indierockgrupper", "id": 519101}, {"name": "Svenska_metalgrupper", "id": 664669}, {"name": "Upplösta_svenska_rockgrupper", "id": 1231362}, {"name": "Svenska_progressiva_rockgrupper", "id": 1591958}, {"name": "Låtar_av_Joakim_Berg", "id": 1009857}, {"name": "Singlar_av_Kent", "id": 1062300}]}