{"name": "Isolatspråk", "id": 53517, "predecessors": [{"name": "Lingvistik", "id": 111944}], "successors": [{"name": "Koreanskspråkiga_filmer", "id": 1605918}, {"name": "Koreanska_ord_och_uttryck", "id": 2802306}, {"name": "Koreanskspråkiga_TV-serier", "id": 4961543}, {"name": "Koreanska_alfabetet", "id": 5313311}, {"name": "Japanskspråkiga_författare", "id": 243864}, {"name": "Japanska_ord_och_uttryck", "id": 1176610}, {"name": "Japanskspråkiga_filmer", "id": 1720521}, {"name": "Anime_(TV)", "id": 390266}]}