{"name": "Däggdjur", "id": 53647, "predecessors": [{"name": "Biologi", "id": 50632}], "successors": [{"name": "Fladdermöss", "id": 124353}, {"name": "Förhistoriska_däggdjur", "id": 1035104}, {"name": "Guldmullvadar", "id": 1113424}, {"name": "Däggdjurssynonymer", "id": 2510760}, {"name": "Marsvinsartade_gnagare", "id": 1055050}, {"name": "Råttartade_gnagare", "id": 1070651}, {"name": "Påsmöss", "id": 2494135}, {"name": "Kindpåsråttor", "id": 2494300}, {"name": "Mårddjur", "id": 134508}, {"name": "Kattdjur", "id": 257412}, {"name": "Manguster", "id": 519038}, {"name": "Viverrider", "id": 699547}, {"name": "Brednäsor", "id": 1031200}, {"name": "Strepsirrhini", "id": 1032422}, {"name": "Svindjur", "id": 517171}, {"name": "Pipharar", "id": 6286968}, {"name": "Pungråttor", "id": 1311939}, {"name": "Fåframtandade_pungdjur", "id": 1871493}, {"name": "Slidhornsdjur", "id": 166195}, {"name": "Hjortdjur", "id": 437915}, {"name": "Rävar", "id": 941225}, {"name": "Berömda_hundar", "id": 609865}, {"name": "Hundhållning", "id": 1256863}, {"name": "Navigationsrutor-Hundar", "id": 1437197}, {"name": "Sällskapshundar", "id": 755228}, {"name": "Spetsar_och_urhundar", "id": 755232}, {"name": "Terrier", "id": 755236}, {"name": "Vall-,_boskaps-_och_herdehundar", "id": 755237}, {"name": "Schnauzer_och_pinscher,_molosser_och_bergshundar_samt_sennenhundar", "id": 755239}, {"name": "Drivande_hundar,_samt_sök-_och_spårhundar", "id": 755243}, {"name": "Stående_fågelhundar", "id": 755245}, {"name": "Vinthundar", "id": 755247}, {"name": "Stötande_och_apporterande_hundar", "id": 1020998}, {"name": "Hundrastyper", "id": 1428880}, {"name": "Elefanter", "id": 418916}, {"name": "Hästar", "id": 130592}, {"name": "Markattartade_apor", "id": 471017}, {"name": "Sovmöss", "id": 481443}, {"name": "Ekorrar", "id": 1506750}, {"name": "Fiktiva_hundar", "id": 721108}, {"name": "Mullvadsdjur", "id": 478693}, {"name": "Näbbmöss", "id": 478719}, {"name": "Travhästar_med_statistik_över_starter", "id": 8315757}, {"name": "Däggdjur_i_palearktiska_regionen", "id": 1529230}, {"name": "Däggdjur_i_nearktiska_regionen", "id": 1529233}, {"name": "Däggdjur_i_orientaliska_regionen", "id": 1529238}, {"name": "Däggdjur_i_etiopiska_regionen", "id": 1529244}, {"name": "Däggdjur_i_neotropiska_regionen", "id": 1529247}, {"name": "Däggdjur_i_australiska_regionen", "id": 1529268}, {"name": "Däggdjur_i_oceaniska_regionen", "id": 1529272}, {"name": "Rovpungdjur", "id": 1136855}, {"name": "Harar_(släkte)", "id": 2495359}, {"name": "Kaninraser", "id": 369874}, {"name": "Förmänniskor", "id": 86741}, {"name": "Amerikanska_travhästar", "id": 6925052}, {"name": "Franska_travhästar", "id": 6925054}, {"name": "Italienska_travhästar", "id": 6925056}, {"name": "Svenska_varmblodiga_travhästar", "id": 8441109}, {"name": "Hästar_som_tränats_av_Lutfi_Kolgjini", "id": 8049031}, {"name": "Hästar_som_tränats_av_Stefan_Melander", "id": 8049032}, {"name": "Avkommor_efter_Ready_Cash", "id": 8263511}, {"name": "Fiktiva_björnar", "id": 701515}, {"name": "Fiktiva_möss_och_råttor", "id": 865644}, {"name": "Fiktiva_katter", "id": 706167}, {"name": "Heraldiska_vapen_med_lejon", "id": 925115}, {"name": "Varulvsfilmer", "id": 648707}, {"name": "Hästar_som_vunnit_Elitloppet", "id": 8049034}, {"name": "Hästar_som_vunnit_Prix_d'Amérique", "id": 8049035}, {"name": "Hästar_som_vunnit_Svenskt_Travderby", "id": 8347148}, {"name": "Hästar_som_vunnit_Hambletonian_Stakes", "id": 8370895}, {"name": "Hästar_som_vunnit_Prix_de_France", "id": 8412627}, {"name": "Hästar_som_vunnit_Svenskt_Trav-Kriterium", "id": 8597122}]}