{"name": "Botanik", "id": 54276, "predecessors": [{"name": "Biologi", "id": 50632}], "successors": [{"name": "Jordarter", "id": 157792}, {"name": "Växtanatomi", "id": 240052}, {"name": "Växtfysiologi", "id": 241934}, {"name": "Auktorsförkortningar", "id": 341291}, {"name": "Växtmorfologi", "id": 1441588}, {"name": "Träd", "id": 58131}, {"name": "Alger", "id": 112492}, {"name": "Växtlistor", "id": 239524}, {"name": "Bladmossor", "id": 389489}, {"name": "Sommarblommor", "id": 505982}, {"name": "Levermossor", "id": 871313}, {"name": "Kärlväxter", "id": 4018339}, {"name": "Bl_Växtindex", "id": 272489}, {"name": "Be_Växtindex", "id": 273765}, {"name": "Bo_Växtindex", "id": 274214}, {"name": "Ba_Växtindex", "id": 276251}, {"name": "Br_Växtindex", "id": 276279}, {"name": "Jä_Växtindex", "id": 272919}, {"name": "Jo_Växtindex", "id": 272978}, {"name": "Ja_Växtindex", "id": 272986}, {"name": "Ki_Växtindex", "id": 272930}, {"name": "Ka_Växtindex", "id": 273812}, {"name": "Ko_Växtindex", "id": 276263}, {"name": "Kl_Växtindex", "id": 276290}, {"name": "Kn_Växtindex", "id": 276291}, {"name": "Kr_Växtindex", "id": 276333}, {"name": "Kä_Växtindex", "id": 278383}, {"name": "Al_Växtindex", "id": 272989}, {"name": "Am_Växtindex", "id": 276245}, {"name": "Dv_Växtindex", "id": 276282}, {"name": "Do_Växtindex", "id": 321710}, {"name": "Fl_Växtindex", "id": 272991}, {"name": "Fj_Växtindex", "id": 276261}, {"name": "Fi_Växtindex", "id": 280745}, {"name": "Gr_Växtindex", "id": 276285}, {"name": "Gu_Växtindex", "id": 276316}, {"name": "Gl_Växtindex", "id": 372810}, {"name": "Ha_Växtindex", "id": 276262}, {"name": "Hä_Växtindex", "id": 276288}, {"name": "La_Växtindex", "id": 273785}, {"name": "Li_Växtindex", "id": 276244}, {"name": "Lu_Växtindex", "id": 281550}, {"name": "Ma_Växtindex", "id": 276265}, {"name": "Mo_Växtindex", "id": 276317}, {"name": "Or_Växtindex", "id": 280738}, {"name": "Pa_Växtindex", "id": 273004}, {"name": "Pi_Växtindex", "id": 276298}, {"name": "Pr_Växtindex", "id": 276368}, {"name": "Po_Växtindex", "id": 280703}, {"name": "Rö_Växtindex", "id": 272998}, {"name": "Ro_Växtindex", "id": 276526}, {"name": "Sk_Växtindex", "id": 273017}, {"name": "Sa_Växtindex", "id": 273780}, {"name": "Si_Växtindex", "id": 274211}, {"name": "So_Växtindex", "id": 276270}, {"name": "Sp_Växtindex", "id": 276303}, {"name": "St_Växtindex", "id": 276304}, {"name": "Sv_Växtindex", "id": 276306}, {"name": "Sm_Växtindex", "id": 278435}, {"name": "Ta_Växtindex", "id": 276248}, {"name": "Tr_Växtindex", "id": 276308}, {"name": "Vi_Växtindex", "id": 273782}, {"name": "Va_Växtindex", "id": 276254}, {"name": "Vå_Växtindex", "id": 276324}, {"name": "Åk_Växtindex", "id": 273794}, {"name": "Än_Växtindex", "id": 273795}, {"name": "Durio", "id": 1075708}, {"name": "Silverbuskar", "id": 4518839}, {"name": "Flugtrumpetväxter", "id": 194664}, {"name": "Växtsjukdomar", "id": 117167}, {"name": "Afrikas_flora", "id": 761645}, {"name": "Asiens_flora", "id": 935969}, {"name": "Europas_flora", "id": 994021}, {"name": "Sydamerikas_flora", "id": 1098401}, {"name": "USA:s_flora", "id": 1530720}, {"name": "Australiens_flora", "id": 1098356}, {"name": "Sveriges_flora", "id": 760149}, {"name": "Kinas_flora", "id": 935908}, {"name": "Sydafrikas_flora", "id": 1098341}, {"name": "Irans_flora", "id": 1216520}, {"name": "Japans_flora", "id": 1711567}, {"name": "Rysslands_flora", "id": 1711582}, {"name": "Kazakstans_flora", "id": 3967123}, {"name": "Turkiets_flora", "id": 8661397}, {"name": "Syriens_flora", "id": 8661410}, {"name": "Frankrikes_flora", "id": 8661556}, {"name": "Italiens_flora", "id": 8661557}, {"name": "Växter_i_Mexiko", "id": 764811}, {"name": "Växter_i_Argentina", "id": 765409}, {"name": "Växter_i_Chile", "id": 766340}, {"name": "Tvåhjärtbladiga_blomväxter", "id": 1882180}, {"name": "Enhjärtbladiga_blomväxter", "id": 1882296}, {"name": "Växtgeografer", "id": 4878549}, {"name": "Enskilda_träd_i_Sverige", "id": 1916796}, {"name": "Odlade_växter", "id": 130030}, {"name": "Giftiga_växter", "id": 516048}, {"name": "Småplaneter_namngivna_efter_växter", "id": 8156538}, {"name": "Frukter", "id": 67864}, {"name": "Medicinalväxter", "id": 517500}, {"name": "Färgväxter", "id": 806879}]}