{"name": "Kanadensiska_skådespelare", "id": 55525, "predecessors": [{"name": "Naturgeografi", "id": 111478}, {"name": "Topp", "id": 113605}, {"name": "Film", "id": 50715}], "successors": [{"name": "Kanadensiska_komiker", "id": 146615}, {"name": "Kanadensiska_röstskådespelare", "id": 743175}, {"name": "Kanadensiska_TV-skådespelare", "id": 1469346}, {"name": "Kanadensiska_skådespelare_under_1900-talet", "id": 3915597}, {"name": "Kanadensiska_skådespelare_under_2000-talet", "id": 3915600}, {"name": "Skådespelare_från_Toronto", "id": 2784992}, {"name": "Skådespelare_från_Ontario", "id": 2785038}]}