{"name": "Los_Angeles", "id": 57010, "predecessors": [{"name": "Los_Angeles_County", "id": 648785}, {"name": "Orter_i_Kalifornien", "id": 296176}, {"name": "Sport", "id": 55124}], "successors": [{"name": "Personer_från_Los_Angeles", "id": 1412057}, {"name": "Stadsdelar_i_Los_Angeles", "id": 6333917}, {"name": "Idrottare_från_Los_Angeles", "id": 1612174}, {"name": "Hollywoods_historia_och_kultur", "id": 3872907}, {"name": "Los_Angeles_under_1900-talet", "id": 8360392}, {"name": "Los_Angeles_under_2000-talet", "id": 8360393}, {"name": "Los_Angeles_i_fiktion", "id": 1094201}, {"name": "Musik_i_Los_Angeles", "id": 1253803}, {"name": "Skådespelare_från_Los_Angeles", "id": 1542357}, {"name": "Företag_i_Los_Angeles", "id": 3938099}]}