{"name": "Företag_listade_på_NYSE", "id": 888083, "predecessors": [{"name": "Aktier", "id": 187275}, {"name": "Mikroekonomi", "id": 225663}], "successors": [{"name": "McDonald's", "id": 168465}, {"name": "Walt_Disney_Company", "id": 372387}, {"name": "IBM", "id": 1210955}, {"name": "Coca-Cola", "id": 1405350}, {"name": "BP", "id": 1721890}, {"name": "Boeing", "id": 1874552}, {"name": "Lockheed_Martin", "id": 2340142}, {"name": "General_Dynamics", "id": 2357422}, {"name": "Raytheon_Company", "id": 2365842}, {"name": "General_Electric", "id": 3935288}, {"name": "Berkshire_Hathaway", "id": 5055142}, {"name": "MGM_Resorts_International", "id": 8229641}]}